encrep/__init__.py
encrep/__main__.py
encrep/main.py
encrep-1.0.5.dist-info/LICENSE
encrep-1.0.5.dist-info/METADATA
encrep-1.0.5.dist-info/WHEEL
encrep-1.0.5.dist-info/entry_points.txt
encrep-1.0.5.dist-info/RECORD
