Metadata-Version: 2.3
Name: encrep
Version: 1.0.5
Summary: CLI tool for dumping and restoring Git repos via AWS S3.
License: MIT
Author: Anatoly Petrov
Author-email: petrov.projects@gmail.com
Requires-Python: >=3.13
Classifier: License :: OSI Approved :: MIT License
Classifier: Programming Language :: Python :: 3
Classifier: Programming Language :: Python :: 3.13
Requires-Dist: boto3 (>=1.40.21,<2.0.0)
Requires-Dist: cryptography (>=45.0.6,<46.0.0)
Requires-Dist: moto[s3] (>=5.1.11,<6.0.0)
Requires-Dist: pytest (>=8.4.1,<9.0.0)
Requires-Dist: typer (>=0.17.3,<0.18.0)
Project-URL: Homepage, https://github.com/AnatoliyProjects/encrep
